{
  "unpublishedCollection": {
    "name": "JSObject2",
    "pageId": "表单测试",
    "pluginId": "js-plugin",
    "pluginType": "JS",
    "actions": [],
    "archivedActions": [],
    "body": "export default {\n\tmyVar1: [],\n\tmyVar2: {},\n\tmyFun1: () => {\n\t\t//write code here\n\t},\n\tmyFun2: async () => {\n\t\t//use async-await or promises\n\t}\n}",
    "variables": [
      {
        "name": "myVar1",
        "value": "[]"
      },
      {
        "name": "myVar2",
        "value": "{}"
      }
    ],
    "userPermissions": []
  },
  "id": "表单测试_JSObject2",
  "deleted": false,
  "gitSyncId": "63f08b6dde5d5825c7acb93c_63f0c409de5d5825c7acba59"
}